payment_page_sdk/__init__.py
payment_page_sdk/callback.py
payment_page_sdk/gate.py
payment_page_sdk/payment.py
payment_page_sdk/payment_page.py
payment_page_sdk/process_exception.py
payment_page_sdk/signature_handler.py
flashpay_sdk-1.0.7.dist-info/METADATA
flashpay_sdk-1.0.7.dist-info/WHEEL
flashpay_sdk-1.0.7.dist-info/top_level.txt
flashpay_sdk-1.0.7.dist-info/RECORD
